iugu/__init__.py
iugu/customer.py
iugu_sdk-0.0.1.dist-info/LICENSE
iugu_sdk-0.0.1.dist-info/METADATA
iugu_sdk-0.0.1.dist-info/WHEEL
iugu_sdk-0.0.1.dist-info/top_level.txt
iugu_sdk-0.0.1.dist-info/RECORD
